hera_opm/VERSION
hera_opm/__init__.py
hera_opm/_version.py
hera_opm/mf_tools.py
hera_opm/utils.py
hera_opm/data/__init__.py
hera_opm/data/zen.2458043.40141.HH.uvh5
hera_opm/data/zen.2458043.40887.HH.uvh5
hera_opm/data/zen.2458043.41632.HH.uvh5
hera_opm/data/zen.2458044.40141.HH.uvh5
hera_opm/data/zen.2458044.40886.HH.uvh5
hera_opm/data/zen.2458044.41632.HH.uvh5
hera_opm/data/zen.2458045.40140.HH.uvh5
hera_opm/data/zen.2458045.40886.HH.uvh5
hera_opm/data/zen.2458045.41632.HH.uvh5
hera_opm/data/sample_config/hera_rtp.toml
hera_opm/data/sample_config/idr2.toml
hera_opm/data/sample_config/nrao_rtp.toml
hera_opm/data/sample_config/nrao_rtp_chunk_size.toml
hera_opm/data/sample_config/nrao_rtp_chunk_size_all.toml
hera_opm/data/sample_config/nrao_rtp_nopol.toml
hera_opm/data/sample_config/nrao_rtp_options.toml
hera_opm/data/sample_config/nrao_rtp_setup_teardown.toml
hera_opm/data/sample_config/nrao_rtp_stride_length.toml
hera_opm/data/sample_task_scripts/_common.sh
hera_opm/data/sample_task_scripts/do_ANT_METRICS.sh
hera_opm/data/sample_task_scripts/do_FIRSTCAL.sh
hera_opm/data/sample_task_scripts/do_FIRSTCAL_METRICS.sh
hera_opm/data/sample_task_scripts/do_OMNICAL.sh
hera_opm/data/sample_task_scripts/do_OMNICAL_METRICS.sh
hera_opm/data/sample_task_scripts/do_OMNI_APPLY.sh
hera_opm/data/sample_task_scripts/do_XRFI.sh
hera_opm/data/sample_task_scripts/do_XRFI_APPLY.sh
hera_opm/data/test_input/zen.2458085.12551.xx.HH.uv.ANT_METRICS.xx.log
hera_opm/data/test_input/zen.2458085.12551.xx.HH.uv.ANT_METRICS.xy.log
hera_opm/data/test_input/zen.2458085.12551.xx.HH.uv.ANT_METRICS.yx.log
hera_opm/data/test_input/zen.2458085.12551.xx.HH.uv.ANT_METRICS.yy.log
hera_opm/data/test_output/test.nrao_rtp.cfg.mf
hera_opm/tests/__init__.py
hera_opm/tests/test_lstbin_makeflow.py
hera_opm/tests/test_mf_tools.py
hera_opm/tests/test_utils.py
hera_opm/tests/bad_configs/bad_example.toml
hera_opm/tests/bad_configs/bad_example_obsid_list.toml
hera_opm/tests/bad_configs/bad_missing_prereq.toml
hera_opm-1.4.0.dist-info/LICENSE
hera_opm-1.4.0.dist-info/METADATA
hera_opm-1.4.0.dist-info/WHEEL
hera_opm-1.4.0.dist-info/top_level.txt
hera_opm-1.4.0.dist-info/RECORD
