Metadata-Version: 2.1
Name: hera_opm
Version: 1.4.0
Summary: offline-processing and pipeline managment for HERA data analysis
Home-page: https://github.com/HERA-Team/hera_opm
Author: HERA Team
License: BSD
License-File: LICENSE
Requires-Dist: toml >=0.9.4
Provides-Extra: package
Requires-Dist: build ; extra == 'package'
Provides-Extra: test
Requires-Dist: hera-calibration >=3.3.0 ; extra == 'test'
Requires-Dist: pytest ; extra == 'test'
Requires-Dist: pytest-cov ; extra == 'test'
